README.txt
setup.cfg
setup.py
doc/ChangeLog.txt
doc/Makefile
doc/make.bat
doc/source/ChangeLog.rst
doc/source/Tutorial_ModelGraph.pdf
doc/source/conf.py
doc/source/index.rst
doc/source/references.rst
doc/source/tutorial.rst
doc/source/_static/copybutton.js
src/admin/__init__.py
src/admin/distribute.py
src/admin/install.py
src/admin/multidistribute.py
src/cellnopt/__init__.py
src/cellnopt.admin.egg-info/PKG-INFO
src/cellnopt.admin.egg-info/SOURCES.txt
src/cellnopt.admin.egg-info/dependency_links.txt
src/cellnopt.admin.egg-info/entry_points.txt
src/cellnopt.admin.egg-info/namespace_packages.txt
src/cellnopt.admin.egg-info/requires.txt
src/cellnopt.admin.egg-info/top_level.txt
src/cellnopt/admin/__init__.py
test/__init__.py
test/test_distribute.py
test/test_install.py
test/test_multi_distribute.py