Metadata-Version: 1.1
Name: cellnopt.admin
Version: 0.2.3
Summary: Administrative tools used to manage cellnopt software (python and R)
Home-page: ['http://pythonhosted.org/cellnopt.admin']
Author: Thomas Cokelaer
Author-email: cokelaer@ebi.ac.uk
License: GPL
Download-URL: ['http://pypi.python.org/pypi/cellnopt.admin']
Keywords: CellNOpt
Platform: Linux
Platform: Unix
Platform: MacOsX
Platform: Windows
Classifier: Development Status :: 4 - Beta
Classifier: Intended Audience :: Developers
Classifier: Intended Audience :: Science/Research
Classifier: License :: OSI Approved :: GNU Library or Lesser General Public License (LGPL)
Classifier: Operating System :: OS Independent
Classifier: Programming Language :: Python :: 2.7
Classifier: Topic :: Software Development :: Libraries :: Python Modules
Classifier: Topic :: Scientific/Engineering :: Bio-Informatics
Classifier: Topic :: Scientific/Engineering :: Information Analysis
Classifier: Topic :: Scientific/Engineering :: Mathematics
Classifier: Topic :: Scientific/Engineering :: Physics
